libecm/__init__.py
libecm/ecm_sk12.cpython-37m-arm-linux-gnueabihf.so
libecm/ecm_sk16.cpython-37m-arm-linux-gnueabihf.so
libecm/ecm_xf.cpython-37m-arm-linux-gnueabihf.so
libecm/ecmxf.py
libecm/sk12.py
libecm/sk16.py
libecm/plugins/hexinSigmoid.py
libecm/servo/elmo_gold_pdo_mapping.py
libecm/servo/ls_pdo_mapping.py
libecm/servo/universal_pdo_mapping.py
libecm/test/test_ecmxf_elmo.py
libecm-1.2.dist-info/LICENSE
libecm-1.2.dist-info/METADATA
libecm-1.2.dist-info/WHEEL
libecm-1.2.dist-info/top_level.txt
libecm-1.2.dist-info/RECORD
